WebPy_GraphQL-3.0.1.dist-info/DESCRIPTION.rst
WebPy_GraphQL-3.0.1.dist-info/METADATA
WebPy_GraphQL-3.0.1.dist-info/RECORD
WebPy_GraphQL-3.0.1.dist-info/WHEEL
WebPy_GraphQL-3.0.1.dist-info/metadata.json
WebPy_GraphQL-3.0.1.dist-info/top_level.txt
webpy_graphql/__init__.py
webpy_graphql/graphqlview.py
webpy_graphql/init_subclass_meta.py
webpy_graphql/utils.py
webpy_graphql/templates/graph.html
