Metadata-Version: 2.0
Name: WebPy-GraphQL
Version: 3.0.1
Summary: Adds GraphQL support to your WebPy application
Home-page: https://github.com/Igor-britecore/webpy-graphql
Author: Igor Kozintsev
Author-email: ig.kozintsev@gmail.com
License: MIT
Keywords: api graphql protocol rest webpy grapene
Platform: any
Classifier: Development Status :: 3 - Alpha
Classifier: Intended Audience :: Developers
Classifier: Topic :: Software Development :: Libraries
Classifier: Programming Language :: Python :: 2.7
Classifier: Programming Language :: Python :: Implementation :: PyPy
Classifier: License :: OSI Approved :: MIT License
Requires-Dist: web.py
Requires-Dist: werkzeug
Requires-Dist: graphql-server-core (>=1.0.dev)
Requires-Dist: graphql-core (>=1.0)
Requires-Dist: six
Requires-Dist: paste
